CHANGELOG.txt
LICENSE.txt
MANIFEST.in
README.txt
setup.py
Lib/site-packages/easy_install.py
Lib/site-packages/pip/__init__.py
Lib/site-packages/pip/__main__.py
Lib/site-packages/pip-19.0.3.dist-info/LICENSE.txt
Lib/site-packages/pip-19.0.3.dist-info/entry_points.txt
Lib/site-packages/pip-19.0.3.dist-info/top_level.txt
Lib/site-packages/pip/_internal/__init__.py
Lib/site-packages/pip/_internal/build_env.py
Lib/site-packages/pip/_internal/cache.py
Lib/site-packages/pip/_internal/configuration.py
Lib/site-packages/pip/_internal/download.py
Lib/site-packages/pip/_internal/exceptions.py
Lib/site-packages/pip/_internal/index.py
Lib/site-packages/pip/_internal/locations.py
Lib/site-packages/pip/_internal/pep425tags.py
Lib/site-packages/pip/_internal/pyproject.py
Lib/site-packages/pip/_internal/resolve.py
Lib/site-packages/pip/_internal/wheel.py
Lib/site-packages/pip/_internal/cli/__init__.py
Lib/site-packages/pip/_internal/cli/autocompletion.py
Lib/site-packages/pip/_internal/cli/base_command.py
Lib/site-packages/pip/_internal/cli/cmdoptions.py
Lib/site-packages/pip/_internal/cli/main_parser.py
Lib/site-packages/pip/_internal/cli/parser.py
Lib/site-packages/pip/_internal/cli/status_codes.py
Lib/site-packages/pip/_internal/commands/__init__.py
Lib/site-packages/pip/_internal/commands/check.py
Lib/site-packages/pip/_internal/commands/completion.py
Lib/site-packages/pip/_internal/commands/configuration.py
Lib/site-packages/pip/_internal/commands/download.py
Lib/site-packages/pip/_internal/commands/freeze.py
Lib/site-packages/pip/_internal/commands/hash.py
Lib/site-packages/pip/_internal/commands/help.py
Lib/site-packages/pip/_internal/commands/install.py
Lib/site-packages/pip/_internal/commands/list.py
Lib/site-packages/pip/_internal/commands/search.py
Lib/site-packages/pip/_internal/commands/show.py
Lib/site-packages/pip/_internal/commands/uninstall.py
Lib/site-packages/pip/_internal/commands/wheel.py
Lib/site-packages/pip/_internal/models/__init__.py
Lib/site-packages/pip/_internal/models/candidate.py
Lib/site-packages/pip/_internal/models/format_control.py
Lib/site-packages/pip/_internal/models/index.py
Lib/site-packages/setuptools-40.8.0.dist-info/dependency_links.txt
Lib/site-packages/setuptools-40.8.0.dist-info/entry_points.txt
Lib/site-packages/setuptools-40.8.0.dist-info/top_level.txt
pentesterbasicbankaccount.egg-info/SOURCES.txt
pentesterbasicbankaccount.egg-info/dependency_links.txt
pentesterbasicbankaccount.egg-info/entry_points.txt
pentesterbasicbankaccount.egg-info/requires.txt
pentesterbasicbankaccount.egg-info/top_level.txt
pentesterbasicbankaccount1.egg-info/PKG-INFO
pentesterbasicbankaccount1.egg-info/SOURCES.txt
pentesterbasicbankaccount1.egg-info/dependency_links.txt
pentesterbasicbankaccount1.egg-info/entry_points.txt
pentesterbasicbankaccount1.egg-info/requires.txt
pentesterbasicbankaccount1.egg-info/top_level.txt