Metadata-Version: 2.1
Name: pentesterbasicbankaccount
Version: 0.0.2
Summary: Allows you to create a simple bank account
Home-page: UNKNOWN
Author: pentester56
Author-email: helloworld@gmail.com
License: MIT
Platform: UNKNOWN
Classifier: Development Status :: 5 - Production/Stable
Classifier: Intended Audience :: Education
Classifier: Operating System :: OS Independent
Classifier: License :: OSI Approved :: MIT License
Classifier: Programming Language :: Python :: 3
